{
	"coc.preferences.formatOnSaveFiletypes": [
		"css",
		"markdown",
		"javascript",
		"graphql",
		"html",
		"yaml",
		"json",
		"python",
		"rust",
		"java"
	],
	"diagnostic.checkCurrentLine": true,
	"clangd.inlayHints.enable": false,
	"python.linting.enabled": true,
	"python.linting.pylintEnabled": true,
	"snippets.ultisnips.directories": [
		"UltiSnips",
		"~/.config/nvim/utils/snips"
	],
	"python.linting.pylintArgs": [
		"--extension-pkg-whitelist=pygame"
	],
	"snippets.ultisnips.pythonPrompt": false
}
